pentest_helper/__init__.py
pentest_helper/__main__.py
pentest_helper/cme_functions.py
pentest_helper/consolidate_functions.py
pentest_helper/consts.py
pentest_helper/init_functions.py
pentest_helper/nmap_functions.py
pentest_helper/utils.py
pentest_helper-0.0.2.dist-info/LICENSE
pentest_helper-0.0.2.dist-info/METADATA
pentest_helper-0.0.2.dist-info/WHEEL
pentest_helper-0.0.2.dist-info/entry_points.txt
pentest_helper-0.0.2.dist-info/top_level.txt
pentest_helper-0.0.2.dist-info/RECORD
