Metadata-Version: 2.1
Name: pentest-helper
Version: 0.0.2
Summary: Help init and run basic commands during a pentest assessment
Home-page: https://github.com/nazime/pentest_helper
Author: Nazime LAKEHAL
Author-email: nazime.lkh@gmail.com
Maintainer: Nazime LAKEHAL
Maintainer-email: nazime.lkh@gmail.com
License: MIT
Project-URL: Documentation, https://pentest_helper.readthedocs.org/
Project-URL: Bug Tracker, https://github.com/nazime/pentest_helper/issues
Project-URL: Source Code, https://github.com/nazime/pentest_helper
Platform: UNKNOWN
Classifier: Development Status :: 3 - Alpha
Classifier: Natural Language :: English
Classifier: License :: OSI Approved :: MIT License
Classifier: Programming Language :: Python
Classifier: Programming Language :: Python :: 3.7
Classifier: Programming Language :: Python :: 3.8
Requires-Python: >=3.6
Requires-Dist: koalak (>=0.3.1)
Provides-Extra: dev
Requires-Dist: coverage ; extra == 'dev'
Requires-Dist: hypothesis ; extra == 'dev'
Requires-Dist: pytest (>=4.3.0) ; extra == 'dev'
Requires-Dist: mkdocs ; extra == 'dev'
Requires-Dist: pre-commit ; extra == 'dev'
Provides-Extra: docs
Requires-Dist: mkdocs ; extra == 'docs'
Provides-Extra: tests
Requires-Dist: coverage ; extra == 'tests'
Requires-Dist: hypothesis ; extra == 'tests'
Requires-Dist: pytest (>=4.3.0) ; extra == 'tests'
Provides-Extra: travis
Requires-Dist: coverage ; extra == 'travis'
Requires-Dist: hypothesis ; extra == 'travis'
Requires-Dist: pytest (>=4.3.0) ; extra == 'travis'
Requires-Dist: mkdocs ; extra == 'travis'
Requires-Dist: pre-commit ; extra == 'travis'
Requires-Dist: tox ; extra == 'travis'
Requires-Dist: codecov ; extra == 'travis'
